{
  "filePath": ".spec-workflow/specs/content-management-v1/requirements.md",
  "currentVersion": 2,
  "snapshots": [
    {
      "version": 1,
      "filename": "snapshot-001.json",
      "timestamp": "2026-01-06T03:44:50.026Z",
      "trigger": "initial",
      "approvalId": "approval_1767671089993_rd1mveztq",
      "approvalTitle": "功能需求文档 (requirements.md) - 发布、查看、搜索功能"
    },
    {
      "version": 2,
      "filename": "snapshot-002.json",
      "timestamp": "2026-01-06T03:45:47.159Z",
      "trigger": "approved",
      "approvalId": "approval_1767671089993_rd1mveztq",
      "approvalTitle": "功能需求文档 (requirements.md) - 发布、查看、搜索功能"
    }
  ]
}